manim_paulie/__init__.py
manim_paulie/pendulum.py
manim_paulie-0.1.0.dist-info/WHEEL
manim_paulie-0.1.0.dist-info/entry_points.txt
manim_paulie-0.1.0.dist-info/METADATA
manim_paulie-0.1.0.dist-info/RECORD
